scigimage/__init__.py
scigimage/core.py
scigimage/effects.py
scigimage/filters.py
scigimage/shapes.py
scigimage/utils.py
tests/__init__.py
tests/test_core.py
tests/test_scigimage.py
scigimage-1.0.0.dist-info/LICENSE
scigimage-1.0.0.dist-info/METADATA
scigimage-1.0.0.dist-info/WHEEL
scigimage-1.0.0.dist-info/top_level.txt
scigimage-1.0.0.dist-info/RECORD
