Metadata-Version: 2.2
Name: scigimage
Version: 1.0.0
Summary: A lightweight library for generating dynamic star maps and animations.
Home-page: https://github.com/Sumedh1599/scigimage
Author: Sumedh Patil
Author-email: admin@aipress.uk
Classifier: Programming Language :: Python :: 3
Classifier: License :: OSI Approved :: MIT License
Classifier: Operating System :: OS Independent
Requires-Python: >=3.6
License-File: LICENSE
Requires-Dist: numpy
Requires-Dist: Pillow
Dynamic: author
Dynamic: author-email
Dynamic: classifier
Dynamic: description
Dynamic: description-content-type
Dynamic: home-page
Dynamic: requires-dist
Dynamic: requires-python
Dynamic: summary
